current_wapi/__init__.py
current_wapi/base.py
current_wapi/wapi.py
temp_wapi-0.0.2.dist-info/METADATA
temp_wapi-0.0.2.dist-info/WHEEL
temp_wapi-0.0.2.dist-info/top_level.txt
temp_wapi-0.0.2.dist-info/RECORD
