Metadata-Version: 2.4
Name: temp_wapi
Version: 0.0.2
Summary: Fetches current temperature for given latitude and longitude
Home-page: https://github.com/Alireza123480/temp_wapi
Author: Alireza Alizadeh
Author-email: alirezaalizadeh3690@gmail.com
Project-URL: Author, https://jobinja.ir/user/HW-3398111
Classifier: Programming Language :: Python :: 3
Classifier: License :: OSI Approved :: MIT License
Classifier: Operating System :: OS Independent
Requires-Python: >=3.6
Requires-Dist: requests
Dynamic: author
Dynamic: author-email
Dynamic: classifier
Dynamic: description
Dynamic: description-content-type
Dynamic: home-page
Dynamic: project-url
Dynamic: requires-dist
Dynamic: requires-python
Dynamic: summary
